Workbook

Sheet PF MF Side by Side
A1: PF & MF ON ONE ROW - INPUT DIFFERENCES AND LIABILITY RECONCILIATION
A2: Formula: DSR (%) = [((MBRE LIC + Lead Life Takaful)/Frequency) + Lead EMI/Frequency + (Staff EMI + Staff Life Takaful)/Frequency + Included Liabilities] x Factor / Total Income x 100.
A3: Liabilities: add Customer_LIB_AMOUNT ONLY when Consider_Obligation=Yes (all assigned rows active). Differences = MF minus PF. Finance Amount is context only, NOT an extra term in DSR.
A4: Own-stored adjustment = Stored DSR ratio x Income / Factor - Monthly Finance Burden - Included Liabilities. + means add liability; - means subtract. It is an inferred equivalent, NOT a verified debt or approved correction.
A5: Equality scenarios keep all MF inputs fixed except liabilities. One targets PF derived DSR; the other targets PF stored DSR. Matching own stored DSR does NOT make PF and MF equal. Negative target liabilities are not feasible debts.
A6: RED fill/text=nonzero values in difference columns ONLY (including rounding-only gaps). GREEN=equal input or reconciled result; AMBER=assumption/caveat. Adjustments remain inferred, not verified liabilities. Frequency=1, Factor=1, missing insurance/staff components=0; blank co-app income=0. Tiny adjustments on green matches are rounding only.
A7: CASE IDENTIFICATION AND DIFFERENCES | H7: TOTAL INCOME | K7: FINANCE AMOUNT (CONTEXT) | N7: MBRE LIC (ASSUMED) | Q7: LEAD LIFE TAKAFUL | T7: LEAD EMI | W7: STAFF EMI (ASSUMED) | Z7: STAFF LIFE TAKAFUL (ASSUMED) | AC7: FREQUENCY | AF7: FACTOR | AI7: INCLUDED LIABILITIES (YES) | AL7: DERIVED DSR | AO7: STORED LEAD_DSR | AR7: DERIVED VERSUS STORED | AT7: ADJUSTMENT TO REPRODUCE OWN STORED DSR | AZ7: MAKE MF EQUAL PF: LIABILITY-ONLY SCENARIOS
A8: Case | B8: PF Application Ref | C8: PF Lead_No | D8: MF Application Ref | E8: MF Lead_No | F8: Match Basis | G8: Remarks | H8: PF Total Income | I8: MF Total Income | J8: Difference Total Income (MF-PF) | K8: PF Finance Amount (context) | L8: MF Finance Amount (context) | M8: Difference Finance Amount (context) (MF-PF) | N8: PF MBRE LIC (assumed) | O8: MF MBRE LIC (assumed) | P8: Difference MBRE LIC (assumed) (MF-PF) | Q8: PF Lead Life Takaful | R8: MF Lead Life Takaful | S8: Difference Lead Life Takaful (MF-PF) | T8: PF Lead EMI | U8: MF Lead EMI | V8: Difference Lead EMI (MF-PF) | W8: PF Staff EMI (assumed) | X8: MF Staff EMI (assumed) | Y8: Difference Staff EMI (assumed) (MF-PF) | Z8: PF Staff Life Takaful (assumed) | AA8: MF Staff Life Takaful (assumed) | AB8: Difference Staff Life Takaful (assumed) (MF-PF) | AC8: PF Frequency | AD8: MF Frequency | AE8: Difference Frequency (MF-PF) | AF8: PF Factor | AG8: MF Factor | AH8: Difference Factor (MF-PF) | AI8: PF Included Liabilities (Yes) | AJ8: MF Included Liabilities (Yes) | AK8: Difference Included Liabilities (Yes) (MF-PF) | AL8: PF Derived DSR | AM8: MF Derived DSR | AN8: Derived DSR Difference (pp) | AO8: PF Stored LEAD_DSR | AP8: MF Stored LEAD_DSR | AQ8: Stored DSR Difference (pp) | AR8: PF Derived Minus Stored (pp) | AS8: MF Derived Minus Stored (pp) | AT8: PF Liability Adjustment (+add / -subtract) | AU8: MF Liability Adjustment (+add / -subtract) | AV8: PF Liabilities After Adjustment | AW8: MF Liabilities After Adjustment | AX8: PF DSR After Adjustment | AY8: MF DSR After Adjustment | AZ8: MF Liability Change to PF Derived DSR | BA8: MF DSR at PF Derived Target | BB8: PF Stored Target DSR | BC8: MF Liability Change to PF Stored DSR | BD8: MF Total Liabilities at PF Stored Target | BE8: MF DSR at PF Stored Target
A9: 1 | B9: PF182386 | C9: LD-00143605 | D9: MF186574 | E9: LD-00147874 | F9: PROVISIONAL | G9: MF-PF: income +0.00; finance amount +50,000.00 (context only); EMI -221.62; life takaful -119.95; included liabilities +41.00. All other DSR components unchanged. Included liabilities 4,541 -> 4,582. PF has included other-installment 4,541; MF has included home-finance 4,582. Provisional pairing: MF predecessor PF182306 differs from supplied PF182386. To reproduce own stored DSR, liability-equivalent adjustment: PF -0.98; MF +14,045.78 (rounding-only when original DSR matches). To make MF equal PF stored 50.92%, change MF liabilities by +299.59, to 4,881.59, keeping MF other inputs fixed. This is a balancing scenario, not evidence that these debts exist or should be removed. | H9: 32020 | I9: 32020 | J9: =I9-H9 -> 0 | K9: 1820000 | L9: 1870000 | M9: =L9-K9 -> 50000 | N9: 0 | O9: 0 | P9: =O9-N9 -> 0 | Q9: 321 | R9: 201.05 | S9: =R9-Q9 -> -119.95 | T9: 11443.56 | U9: 11221.94 | V9: =U9-T9 -> -221.62 | W9: 0 | X9: 0 | Y9: =X9-W9 -> 0 | Z9: 0 | AA9: 0 | AB9: =AA9-Z9 -> 0 | AC9: 1 | AD9: 1 | AE9: =AD9-AC9 -> 0 | AF9: 1 | AG9: 1 | AH9: =AG9-AF9 -> 0 | AI9: =SUM(4541) -> 4541 | AJ9: =SUM(4582) -> 4582 | AK9: =AJ9-AI9 -> 41 | AL9: =(((N9+Q9)/AC9)+(T9/AC9)+((W9+Z9)/AC9)+(AI9))*AF9/H9 -> 0.50923048 | AM9: =(((O9+R9)/AD9)+(U9/AD9)+((X9+AA9)/AD9)+(AJ9))*AG9/I9 -> 0.49984354 | AN9: =(AM9-AL9)*100 -> -0.93869457 | AO9: 0.5092 | AP9: 0.9385 | AQ9: =(AP9-AO9)*100 -> 42.93 | AR9: =(AL9-AO9)*100 -> 0.0030480949 | AS9: =(AM9-AP9)*100 -> -43.865646 | AT9: =(AO9-AL9)*H9/AF9 -> -0.976 | AU9: =(AP9-AM9)*I9/AG9 -> 14045.78 | AV9: =AI9+AT9 -> 4540.024 | AW9: =AJ9+AU9 -> 18627.78 | AX9: =(((N9+Q9)/AC9)+(T9/AC9)+((W9+Z9)/AC9)+(AV9))*AF9/H9 -> 0.5092 | AY9: =(((O9+R9)/AD9)+(U9/AD9)+((X9+AA9)/AD9)+(AW9))*AG9/I9 -> 0.9385 | AZ9: =(AL9-AM9)*I9/AG9 -> 300.57 | BA9: =(((O9+R9)/AD9)+(U9/AD9)+((X9+AA9)/AD9)+(AJ9+AZ9))*AG9/I9 -> 0.50923048 | BB9: =AO9 -> 0.5092 | BC9: =(AO9-AM9)*I9/AG9 -> 299.594 | BD9: =AJ9+BC9 -> 4881.594 | BE9: =(((O9+R9)/AD9)+(U9/AD9)+((X9+AA9)/AD9)+(BD9))*AG9/I9 -> 0.5092
A10: 2 | B10: PF183876 | C10: LD-00145139 | D10: MF187674 | E10: LD-00149064 | F10: Exact PRE_REF_NO | G10: MF-PF: income +0.00; finance amount +471,000.00 (context only); EMI +1,765.03; life takaful -155.33; included liabilities +35,252.28. All other DSR components unchanged. Included liabilities 1,144.60 -> 36,396.88. MF adds home-finance-valid 8,939.85, personal loan 6,000 and home loans 20,312.43. Both stored DSRs need reconciliation. To reproduce own stored DSR, liability-equivalent adjustment: PF +8,333.67; MF -8,039.61 (rounding-only when original DSR matches). To make MF equal PF stored 56.90%, change MF liabilities by -28,528.31, to 7,868.57, keeping MF other inputs fixed. This is a balancing scenario, not evidence that these debts exist or should be removed. | H10: 47938 | I10: 47938 | J10: =I10-H10 -> 0 | K10: 2930000 | L10: 3401000 | M10: =L10-K10 -> 471000 | N10: 0 | O10: 0 | P10: =O10-N10 -> 0 | Q10: 528 | R10: 372.67 | S10: =R10-Q10 -> -155.33 | T10: 17270.45 | U10: 19035.48 | V10: =U10-T10 -> 1765.03 | W10: 0 | X10: 0 | Y10: =X10-W10 -> 0 | Z10: 0 | AA10: 0 | AB10: =AA10-Z10 -> 0 | AC10: 1 | AD10: 1 | AE10: =AD10-AC10 -> 0 | AF10: 1 | AG10: 1 | AH10: =AG10-AF10 -> 0 | AI10: =SUM(1144.6) -> 1144.6 | AJ10: =SUM(1144.6,8939.85,6000,6000,14312.43) -> 36396.88 | AK10: =AJ10-AI10 -> 35252.28 | AL10: =(((N10+Q10)/AC10)+(T10/AC10)+((W10+Z10)/AC10)+(AI10))*AF10/H10 -> 0.39515729 | AM10: =(((O10+R10)/AD10)+(U10/AD10)+((X10+AA10)/AD10)+(AJ10))*AG10/I10 -> 1.1641084 | AN10: =(AM10-AL10)*100 -> 76.895115 | AO10: 0.569 | AP10: 0.9964 | AQ10: =(AP10-AO10)*100 -> 42.74 | AR10: =(AL10-AO10)*100 -> -17.384271 | AS10: =(AM10-AP10)*100 -> 16.770843 | AT10: =(AO10-AL10)*H10/AF10 -> 8333.672 | AU10: =(AP10-AM10)*I10/AG10 -> -8039.6068 | AV10: =AI10+AT10 -> 9478.272 | AW10: =AJ10+AU10 -> 28357.273 | AX10: =(((N10+Q10)/AC10)+(T10/AC10)+((W10+Z10)/AC10)+(AV10))*AF10/H10 -> 0.569 | AY10: =(((O10+R10)/AD10)+(U10/AD10)+((X10+AA10)/AD10)+(AW10))*AG10/I10 -> 0.9964 | AZ10: =(AL10-AM10)*I10/AG10 -> -36861.98 | BA10: =(((O10+R10)/AD10)+(U10/AD10)+((X10+AA10)/AD10)+(AJ10+AZ10))*AG10/I10 -> 0.39515729 | BB10: =AO10 -> 0.569 | BC10: =(AO10-AM10)*I10/AG10 -> -28528.308 | BD10: =AJ10+BC10 -> 7868.572 | BE10: =(((O10+R10)/AD10)+(U10/AD10)+((X10+AA10)/AD10)+(BD10))*AG10/I10 -> 0.569
A11: 3 | B11: PF184910 | C11: LD-00146208 | D11: MF186489 | E11: LD-00147858 | F11: Exact PRE_REF_NO | G11: MF-PF: income +0.00; finance amount -10,000.00 (context only); EMI -697.55; life takaful -7.40; included liabilities +13,259.00. All other DSR components unchanged. PF excludes both 4,921 and 17,348. MF includes 4,921 and 8,338. Contract/type/amount mapping changes need validation. To reproduce own stored DSR, liability-equivalent adjustment: PF -0.71; MF +3,069.60 (rounding-only when original DSR matches). To make MF equal PF stored 49.87%, change MF liabilities by -12,554.76, to 704.24, keeping MF other inputs fixed. This is a balancing scenario, not evidence that these debts exist or should be removed. PF exact-stored implied liabilities are slightly negative due to stored rounding; not a valid debt. | H11: 27600 | I11: 27600 | J11: =I11-H11 -> 0 | K11: 2300000 | L11: 2290000 | M11: =L11-K11 -> -10000 | N11: 0 | O11: 0 | P11: =O11-N11 -> 0 | Q11: 258.18 | R11: 250.78 | S11: =R11-Q11 -> -7.4 | T11: 13506.65 | U11: 12809.1 | V11: =U11-T11 -> -697.55 | W11: 0 | X11: 0 | Y11: =X11-W11 -> 0 | Z11: 0 | AA11: 0 | AB11: =AA11-Z11 -> 0 | AC11: 1 | AD11: 1 | AE11: =AD11-AC11 -> 0 | AF11: 1 | AG11: 1 | AH11: =AG11-AF11 -> 0 | AI11: =0 -> 0 | AJ11: =SUM(4921,8338) -> 13259 | AK11: =AJ11-AI11 -> 13259 | AL11: =(((N11+Q11)/AC11)+(T11/AC11)+((W11+Z11)/AC11)+(AI11))*AF11/H11 -> 0.49872572 | AM11: =(((O11+R11)/AD11)+(U11/AD11)+((X11+AA11)/AD11)+(AJ11))*AG11/I11 -> 0.95358261 | AN11: =(AM11-AL11)*100 -> 45.485688 | AO11: 0.4987 | AP11: 1.0648 | AQ11: =(AP11-AO11)*100 -> 56.61 | AR11: =(AL11-AO11)*100 -> 0.0025724638 | AS11: =(AM11-AP11)*100 -> -11.121739 | AT11: =(AO11-AL11)*H11/AF11 -> -0.71 | AU11: =(AP11-AM11)*I11/AG11 -> 3069.6 | AV11: =AI11+AT11 -> -0.71 | AW11: =AJ11+AU11 -> 16328.6 | AX11: =(((N11+Q11)/AC11)+(T11/AC11)+((W11+Z11)/AC11)+(AV11))*AF11/H11 -> 0.4987 | AY11: =(((O11+R11)/AD11)+(U11/AD11)+((X11+AA11)/AD11)+(AW11))*AG11/I11 -> 1.0648 | AZ11: =(AL11-AM11)*I11/AG11 -> -12554.05 | BA11: =(((O11+R11)/AD11)+(U11/AD11)+((X11+AA11)/AD11)+(AJ11+AZ11))*AG11/I11 -> 0.49872572 | BB11: =AO11 -> 0.4987 | BC11: =(AO11-AM11)*I11/AG11 -> -12554.76 | BD11: =AJ11+BC11 -> 704.24 | BE11: =(((O11+R11)/AD11)+(U11/AD11)+((X11+AA11)/AD11)+(BD11))*AG11/I11 -> 0.4987
A12: 4 | B12: PF188166 | C12: LD-00149573 | D12: MF189169 | E12: LD-00150623 | F12: Exact PRE_REF_NO | G12: MF-PF: income +0.00; finance amount -10,000.00 (context only); EMI -79.92; life takaful -1.22; included liabilities +25,408.41. All other DSR components unchanged. Home finance 9,216 changes No -> Yes; home loan 17,242.41 appears; previously included card 1,050 is absent. Blank co-app income assumed 0; card fields need validation. To reproduce own stored DSR, liability-equivalent adjustment: PF +1,997.38; MF -14,241.31 (rounding-only when original DSR matches). To make MF equal PF stored 46.71%, change MF liabilities by -23,329.89, to 21,146.52, keeping MF other inputs fixed. This is a balancing scenario, not evidence that these debts exist or should be removed. | H12: 64458 | I12: 64458 | J12: =I12-H12 -> 0 | K12: 1310000 | L12: 1300000 | M12: =L12-K12 -> -10000 | N12: 0 | O12: 0 | P12: =O12-N12 -> 0 | Q12: 137.27 | R12: 136.05 | S12: =R12-Q12 -> -1.22 | T12: 8905.68 | U12: 8825.76 | V12: =U12-T12 -> -79.92 | W12: 0 | X12: 0 | Y12: =X12-W12 -> 0 | Z12: 0 | AA12: 0 | AB12: =AA12-Z12 -> 0 | AC12: 1 | AD12: 1 | AE12: =AD12-AC12 -> 0 | AF12: 1 | AG12: 1 | AH12: =AG12-AF12 -> 0 | AI12: =SUM(1050,9375,50,6180,2413) -> 19068 | AJ12: =SUM(2413,9216,6180,50,9375,0,0,17242.41) -> 44476.41 | AK12: =AJ12-AI12 -> 25408.41 | AL12: =(((N12+Q12)/AC12)+(T12/AC12)+((W12+Z12)/AC12)+(AI12))*AF12/H12 -> 0.43611266 | AM12: =(((O12+R12)/AD12)+(U12/AD12)+((X12+AA12)/AD12)+(AJ12))*AG12/I12 -> 0.82903937 | AN12: =(AM12-AL12)*100 -> 39.292671 | AO12: 0.4671 | AP12: 0.6081 | AQ12: =(AP12-AO12)*100 -> 14.1 | AR12: =(AL12-AO12)*100 -> -3.0987337 | AS12: =(AM12-AP12)*100 -> 22.093937 | AT12: =(AO12-AL12)*H12/AF12 -> 1997.3818 | AU12: =(AP12-AM12)*I12/AG12 -> -14241.31 | AV12: =AI12+AT12 -> 21065.382 | AW12: =AJ12+AU12 -> 30235.1 | AX12: =(((N12+Q12)/AC12)+(T12/AC12)+((W12+Z12)/AC12)+(AV12))*AF12/H12 -> 0.4671 | AY12: =(((O12+R12)/AD12)+(U12/AD12)+((X12+AA12)/AD12)+(AW12))*AG12/I12 -> 0.6081 | AZ12: =(AL12-AM12)*I12/AG12 -> -25327.27 | BA12: =(((O12+R12)/AD12)+(U12/AD12)+((X12+AA12)/AD12)+(AJ12+AZ12))*AG12/I12 -> 0.43611266 | BB12: =AO12 -> 0.4671 | BC12: =(AO12-AM12)*I12/AG12 -> -23329.888 | BD12: =AJ12+BC12 -> 21146.522 | BE12: =(((O12+R12)/AD12)+(U12/AD12)+((X12+AA12)/AD12)+(BD12))*AG12/I12 -> 0.4671
A13: 5 | B13: PF191083 | C13: LD-00152624 | D13: MF192489 | E13: LD-00154082 | F13: Exact PRE_REF_NO | G13: MF-PF: income +0.00; finance amount +0.00 (context only); EMI -883.40; life takaful -9.58; included liabilities +0.00. All other DSR components unchanged. NO LIABILITY ROWS supplied at either stage; zero is a comparison scenario, not confirmed zero debt. To reproduce own stored DSR, liability-equivalent adjustment: PF -0.44; MF +17,242.43 (rounding-only when original DSR matches). To make MF equal PF stored 48.27%, change MF liabilities by +892.54, to 892.54, keeping MF other inputs fixed. This is a balancing scenario, not evidence that these debts exist or should be removed. PF exact-stored implied liabilities are slightly negative due to stored rounding; not a valid debt. | H13: 40440 | I13: 40440 | J13: =I13-H13 -> 0 | K13: 3280000 | L13: 3280000 | M13: =L13-K13 -> 0 | N13: 0 | O13: 0 | P13: =O13-N13 -> 0 | Q13: 368.23 | R13: 358.65 | S13: =R13-Q13 -> -9.58 | T13: 19152.6 | U13: 18269.2 | V13: =U13-T13 -> -883.4 | W13: 0 | X13: 0 | Y13: =X13-W13 -> 0 | Z13: 0 | AA13: 0 | AB13: =AA13-Z13 -> 0 | AC13: 1 | AD13: 1 | AE13: =AD13-AC13 -> 0 | AF13: 1 | AG13: 1 | AH13: =AG13-AF13 -> 0 | AI13: =0 -> 0 | AJ13: =0 -> 0 | AK13: =AJ13-AI13 -> 0 | AL13: =(((N13+Q13)/AC13)+(T13/AC13)+((W13+Z13)/AC13)+(AI13))*AF13/H13 -> 0.48271093 | AM13: =(((O13+R13)/AD13)+(U13/AD13)+((X13+AA13)/AD13)+(AJ13))*AG13/I13 -> 0.46062933 | AN13: =(AM13-AL13)*100 -> -2.2081602 | AO13: 0.4827 | AP13: 0.887 | AQ13: =(AP13-AO13)*100 -> 40.43 | AR13: =(AL13-AO13)*100 -> 0.0010929773 | AS13: =(AM13-AP13)*100 -> -42.637067 | AT13: =(AO13-AL13)*H13/AF13 -> -0.442 | AU13: =(AP13-AM13)*I13/AG13 -> 17242.43 | AV13: =AI13+AT13 -> -0.442 | AW13: =AJ13+AU13 -> 17242.43 | AX13: =(((N13+Q13)/AC13)+(T13/AC13)+((W13+Z13)/AC13)+(AV13))*AF13/H13 -> 0.4827 | AY13: =(((O13+R13)/AD13)+(U13/AD13)+((X13+AA13)/AD13)+(AW13))*AG13/I13 -> 0.887 | AZ13: =(AL13-AM13)*I13/AG13 -> 892.98 | BA13: =(((O13+R13)/AD13)+(U13/AD13)+((X13+AA13)/AD13)+(AJ13+AZ13))*AG13/I13 -> 0.48271093 | BB13: =AO13 -> 0.4827 | BC13: =(AO13-AM13)*I13/AG13 -> 892.538 | BD13: =AJ13+BC13 -> 892.538 | BE13: =(((O13+R13)/AD13)+(U13/AD13)+((X13+AA13)/AD13)+(BD13))*AG13/I13 -> 0.4827
A14: 6 | B14: PF193166 | C14: LD-00154791 | D14: MF195006 | E14: LD-00156694 | F14: Exact PRE_REF_NO | G14: MF-PF: income +0.00; finance amount +0.00 (context only); EMI +30.91; life takaful -2.52; included liabilities +14,937.00. All other DSR components unchanged. Home finance 14,937 changes No -> Yes; personal finance 6,654 and auto finance 997 stay included. Both original derived DSRs match their stored values after rounding. This inclusion drives the increase. To reproduce own stored DSR, liability-equivalent adjustment: PF -0.98; MF -1.58 (rounding-only when original DSR matches). To make MF equal PF stored 41.22%, change MF liabilities by -14,966.36, to 7,621.64, keeping MF other inputs fixed. This is a balancing scenario, not evidence that these debts exist or should be removed. | H14: 51925 | I14: 51925 | J14: =I14-H14 -> 0 | K14: 2420000 | L14: 2420000 | M14: =L14-K14 -> 0 | N14: 0 | O14: 0 | P14: =O14-N14 -> 0 | Q14: 267.86 | R14: 265.34 | S14: =R14-Q14 -> -2.52 | T14: 13485.6 | U14: 13516.51 | V14: =U14-T14 -> 30.91 | W14: 0 | X14: 0 | Y14: =X14-W14 -> 0 | Z14: 0 | AA14: 0 | AB14: =AA14-Z14 -> 0 | AC14: 1 | AD14: 1 | AE14: =AD14-AC14 -> 0 | AF14: 1 | AG14: 1 | AH14: =AG14-AF14 -> 0 | AI14: =SUM(6654,997) -> 7651 | AJ14: =SUM(997,6654,14937) -> 22588 | AK14: =AJ14-AI14 -> 14937 | AL14: =(((N14+Q14)/AC14)+(T14/AC14)+((W14+Z14)/AC14)+(AI14))*AF14/H14 -> 0.41221878 | AM14: =(((O14+R14)/AD14)+(U14/AD14)+((X14+AA14)/AD14)+(AJ14))*AG14/I14 -> 0.70043043 | AN14: =(AM14-AL14)*100 -> 28.821165 | AO14: 0.4122 | AP14: 0.7004 | AQ14: =(AP14-AO14)*100 -> 28.82 | AR14: =(AL14-AO14)*100 -> 0.0018777082 | AS14: =(AM14-AP14)*100 -> 0.0030428503 | AT14: =(AO14-AL14)*H14/AF14 -> -0.975 | AU14: =(AP14-AM14)*I14/AG14 -> -1.58 | AV14: =AI14+AT14 -> 7650.025 | AW14: =AJ14+AU14 -> 22586.42 | AX14: =(((N14+Q14)/AC14)+(T14/AC14)+((W14+Z14)/AC14)+(AV14))*AF14/H14 -> 0.4122 | AY14: =(((O14+R14)/AD14)+(U14/AD14)+((X14+AA14)/AD14)+(AW14))*AG14/I14 -> 0.7004 | AZ14: =(AL14-AM14)*I14/AG14 -> -14965.39 | BA14: =(((O14+R14)/AD14)+(U14/AD14)+((X14+AA14)/AD14)+(AJ14+AZ14))*AG14/I14 -> 0.41221878 | BB14: =AO14 -> 0.4122 | BC14: =(AO14-AM14)*I14/AG14 -> -14966.365 | BD14: =AJ14+BC14 -> 7621.635 | BE14: =(((O14+R14)/AD14)+(U14/AD14)+((X14+AA14)/AD14)+(BD14))*AG14/I14 -> 0.4122
A15: 7 | B15: PF197879 | C15: LD-00159632 | D15: MF302327 | E15: LD-00164229 | F15: Exact PRE_REF_NO | G15: MF-PF: income +0.00; finance amount -235,000.00 (context only); EMI -1,603.57; life takaful -23.85; included liabilities +28,008.00. All other DSR components unchanged. Home finance 25,508 and cards 3,000, 750, 1,250 change No -> Yes. Previously included card 2,500 is absent. Net included-liability increase 28,008; contract/card mapping shifts need validation. To reproduce own stored DSR, liability-equivalent adjustment: PF +1.95; MF +4,001.38 (rounding-only when original DSR matches). To make MF equal PF stored 49.39%, change MF liabilities by -26,378.63, to 4,129.37, keeping MF other inputs fixed. This is a balancing scenario, not evidence that these debts exist or should be removed. | H15: 56031 | I15: 56031 | J15: =I15-H15 -> 0 | K15: 3300000 | L15: 3065000 | M15: =L15-K15 -> -235000 | N15: 0 | O15: 0 | P15: =O15-N15 -> 0 | Q15: 340.05 | R15: 316.2 | S15: =R15-Q15 -> -23.85 | T15: 24831.71 | U15: 23228.14 | V15: =U15-T15 -> -1603.57 | W15: 0 | X15: 0 | Y15: =X15-W15 -> 0 | Z15: 0 | AA15: 0 | AB15: =AA15-Z15 -> 0 | AC15: 1 | AD15: 1 | AE15: =AD15-AC15 -> 0 | AF15: 1 | AG15: 1 | AH15: =AG15-AF15 -> 0 | AI15: =SUM(2500) -> 2500 | AJ15: =SUM(25508,3000,750,1250) -> 30508 | AK15: =AJ15-AI15 -> 28008 | AL15: =(((N15+Q15)/AC15)+(T15/AC15)+((W15+Z15)/AC15)+(AI15))*AF15/H15 -> 0.49386518 | AM15: =(((O15+R15)/AD15)+(U15/AD15)+((X15+AA15)/AD15)+(AJ15))*AG15/I15 -> 0.96468633 | AN15: =(AM15-AL15)*100 -> 47.082115 | AO15: 0.4939 | AP15: 1.0361 | AQ15: =(AP15-AO15)*100 -> 54.22 | AR15: =(AL15-AO15)*100 -> -0.0034818226 | AS15: =(AM15-AP15)*100 -> -7.1413666 | AT15: =(AO15-AL15)*H15/AF15 -> 1.9509 | AU15: =(AP15-AM15)*I15/AG15 -> 4001.3791 | AV15: =AI15+AT15 -> 2501.9509 | AW15: =AJ15+AU15 -> 34509.379 | AX15: =(((N15+Q15)/AC15)+(T15/AC15)+((W15+Z15)/AC15)+(AV15))*AF15/H15 -> 0.4939 | AY15: =(((O15+R15)/AD15)+(U15/AD15)+((X15+AA15)/AD15)+(AW15))*AG15/I15 -> 1.0361 | AZ15: =(AL15-AM15)*I15/AG15 -> -26380.58 | BA15: =(((O15+R15)/AD15)+(U15/AD15)+((X15+AA15)/AD15)+(AJ15+AZ15))*AG15/I15 -> 0.49386518 | BB15: =AO15 -> 0.4939 | BC15: =(AO15-AM15)*I15/AG15 -> -26378.629 | BD15: =AJ15+BC15 -> 4129.3709 | BE15: =(((O15+R15)/AD15)+(U15/AD15)+((X15+AA15)/AD15)+(BD15))*AG15/I15 -> 0.4939
A16: 8 | D16: MF183562 | E16: LD-00144780 | F16: No PF supplied | G16: No PF predecessor supplied; no PF/MF equality comparison possible. MF stored 82.58%, derived 82.752669%; liability-equivalent adjustment -29.44 reproduces MF stored DSR only. Not a verified liability correction. | I16: 17050 | L16: 935000 | O16: 0 | R16: 103.9 | U16: 5486.43 | X16: 0 | AA16: 0 | AD16: 1 | AG16: 1 | AJ16: =SUM(2320,6199) -> 8519 | AM16: =(((O16+R16)/AD16)+(U16/AD16)+((X16+AA16)/AD16)+(AJ16))*AG16/I16 -> 0.82752669 | AP16: 0.8258 | AS16: =(AM16-AP16)*100 -> 0.17266862 | AU16: =(AP16-AM16)*I16/AG16 -> -29.44 | AW16: =AJ16+AU16 -> 8489.56 | AY16: =(((O16+R16)/AD16)+(U16/AD16)+((X16+AA16)/AD16)+(AW16))*AG16/I16 -> 0.8258

Sheet PF MF Differences Only
A1: PF vs MF - KEY FIGURES AND DIFFERENCES
A2: PF and MF key figures use normal text. Only nonzero PF-to-MF differences are red. Difference = MF minus PF.
A3: Case 8 contains MF details only; PF and difference fields are blank. Other blank difference cells mean no difference. Figures link to the first tab.
A4: Case | B4: PF App | C4: PF Lead | D4: MF App | E4: MF Lead | F4: PF Fin Amnt | G4: MF Fin Amnt | H4: Fin Amnt diff | I4: PF Takaful | J4: MF Takaful | K4: Life Takaful Diff | L4: PF Lead EMI | M4: MF Lead EMI | N4: EMI Diff | O4: PF Liablity | P4: MF Liab | Q4: Liab Diff | R4: PF DSR | S4: MF DSR | T4: DSR Diff | U4: PF IjaraStDt | V4: PF InsStDt | W4: PF DiffInDays | X4: MF IjaraStDt | Y4: MF InsStDt | Z4: MF DiffInDays
A5: 1 | B5: PF182386 | C5: LD-00143605 | D5: MF186574 | E5: LD-00147874 | F5: ='PF MF Side by Side'!K9 -> 1820000 | G5: ='PF MF Side by Side'!L9 -> 1870000 | H5: ='PF MF Side by Side'!M9 -> 50000 | I5: ='PF MF Side by Side'!Q9 -> 321 | J5: ='PF MF Side by Side'!R9 -> 201.05 | K5: ='PF MF Side by Side'!S9 -> -119.95 | L5: ='PF MF Side by Side'!T9 -> 11443.56 | M5: ='PF MF Side by Side'!U9 -> 11221.94 | N5: ='PF MF Side by Side'!V9 -> -221.62 | O5: ='PF MF Side by Side'!AI9 -> 4541 | P5: ='PF MF Side by Side'!AJ9 -> 4582 | Q5: ='PF MF Side by Side'!AK9 -> 41 | R5: ='PF MF Side by Side'!AO9 -> 0.5092 | S5: ='PF MF Side by Side'!AP9 -> 0.9385 | T5: ='PF MF Side by Side'!AQ9 -> 42.93 | U5: 45954 | V5: 45985 | W5: =V5-U5 -> 31 | X5: 46050 | Y5: 46082 | Z5: =Y5-X5 -> 32
A6: 2 | B6: PF183876 | C6: LD-00145139 | D6: MF187674 | E6: LD-00149064 | F6: ='PF MF Side by Side'!K10 -> 2930000 | G6: ='PF MF Side by Side'!L10 -> 3401000 | H6: ='PF MF Side by Side'!M10 -> 471000 | I6: ='PF MF Side by Side'!Q10 -> 528 | J6: ='PF MF Side by Side'!R10 -> 372.67 | K6: ='PF MF Side by Side'!S10 -> -155.33 | L6: ='PF MF Side by Side'!T10 -> 17270.45 | M6: ='PF MF Side by Side'!U10 -> 19035.48 | N6: ='PF MF Side by Side'!V10 -> 1765.03 | O6: ='PF MF Side by Side'!AI10 -> 1144.6 | P6: ='PF MF Side by Side'!AJ10 -> 36396.88 | Q6: ='PF MF Side by Side'!AK10 -> 35252.28 | R6: ='PF MF Side by Side'!AO10 -> 0.569 | S6: ='PF MF Side by Side'!AP10 -> 0.9964 | T6: ='PF MF Side by Side'!AQ10 -> 42.74 | U6: 45946 | V6: 45977 | W6: =V6-U6 -> 31 | X6: 46071 | Y6: 46109 | Z6: =Y6-X6 -> 38
A7: 3 | B7: PF184910 | C7: LD-00146208 | D7: MF186489 | E7: LD-00147858 | F7: ='PF MF Side by Side'!K11 -> 2300000 | G7: ='PF MF Side by Side'!L11 -> 2290000 | H7: ='PF MF Side by Side'!M11 -> -10000 | I7: ='PF MF Side by Side'!Q11 -> 258.18 | J7: ='PF MF Side by Side'!R11 -> 250.78 | K7: ='PF MF Side by Side'!S11 -> -7.4 | L7: ='PF MF Side by Side'!T11 -> 13506.65 | M7: ='PF MF Side by Side'!U11 -> 12809.1 | N7: ='PF MF Side by Side'!V11 -> -697.55 | O7: ='PF MF Side by Side'!AI11 -> 0 | P7: ='PF MF Side by Side'!AJ11 -> 13259 | Q7: ='PF MF Side by Side'!AK11 -> 13259 | R7: ='PF MF Side by Side'!AO11 -> 0.4987 | S7: ='PF MF Side by Side'!AP11 -> 1.0648 | T7: ='PF MF Side by Side'!AQ11 -> 56.61 | U7: 45964 | V7: 45964 | W7: =V7-U7 -> 0 | X7: 46049 | Y7: 46082 | Z7: =Y7-X7 -> 33
A8: 4 | B8: PF188166 | C8: LD-00149573 | D8: MF189169 | E8: LD-00150623 | F8: ='PF MF Side by Side'!K12 -> 1310000 | G8: ='PF MF Side by Side'!L12 -> 1300000 | H8: ='PF MF Side by Side'!M12 -> -10000 | I8: ='PF MF Side by Side'!Q12 -> 137.27 | J8: ='PF MF Side by Side'!R12 -> 136.05 | K8: ='PF MF Side by Side'!S12 -> -1.22 | L8: ='PF MF Side by Side'!T12 -> 8905.68 | M8: ='PF MF Side by Side'!U12 -> 8825.76 | N8: ='PF MF Side by Side'!V12 -> -79.92 | O8: ='PF MF Side by Side'!AI12 -> 19068 | P8: ='PF MF Side by Side'!AJ12 -> 44476.41 | Q8: ='PF MF Side by Side'!AK12 -> 25408.41 | R8: ='PF MF Side by Side'!AO12 -> 0.4671 | S8: ='PF MF Side by Side'!AP12 -> 0.6081 | T8: ='PF MF Side by Side'!AQ12 -> 14.1 | U8: 46015 | V8: 46046 | W8: =V8-U8 -> 31 | X8: 46093 | Y8: 46112 | Z8: =Y8-X8 -> 19
A9: 5 | B9: PF191083 | C9: LD-00152624 | D9: MF192489 | E9: LD-00154082 | F9: ='PF MF Side by Side'!K13 -> 3280000 | G9: ='PF MF Side by Side'!L13 -> 3280000 | I9: ='PF MF Side by Side'!Q13 -> 368.23 | J9: ='PF MF Side by Side'!R13 -> 358.65 | K9: ='PF MF Side by Side'!S13 -> -9.58 | L9: ='PF MF Side by Side'!T13 -> 19152.6 | M9: ='PF MF Side by Side'!U13 -> 18269.2 | N9: ='PF MF Side by Side'!V13 -> -883.4 | O9: ='PF MF Side by Side'!AI13 -> 0 | P9: ='PF MF Side by Side'!AJ13 -> 0 | R9: ='PF MF Side by Side'!AO13 -> 0.4827 | S9: ='PF MF Side by Side'!AP13 -> 0.887 | T9: ='PF MF Side by Side'!AQ13 -> 40.43 | U9: 46053 | V9: 46053 | W9: =V9-U9 -> 0 | X9: 46128 | Y9: 46148 | Z9: =Y9-X9 -> 20
A10: 6 | B10: PF193166 | C10: LD-00154791 | D10: MF195006 | E10: LD-00156694 | F10: ='PF MF Side by Side'!K14 -> 2420000 | G10: ='PF MF Side by Side'!L14 -> 2420000 | I10: ='PF MF Side by Side'!Q14 -> 267.86 | J10: ='PF MF Side by Side'!R14 -> 265.34 | K10: ='PF MF Side by Side'!S14 -> -2.52 | L10: ='PF MF Side by Side'!T14 -> 13485.6 | M10: ='PF MF Side by Side'!U14 -> 13516.51 | N10: ='PF MF Side by Side'!V14 -> 30.91 | O10: ='PF MF Side by Side'!AI14 -> 7651 | P10: ='PF MF Side by Side'!AJ14 -> 22588 | Q10: ='PF MF Side by Side'!AK14 -> 14937 | R10: ='PF MF Side by Side'!AO14 -> 0.4122 | S10: ='PF MF Side by Side'!AP14 -> 0.7004 | T10: ='PF MF Side by Side'!AQ14 -> 28.82 | U10: 46074 | V10: 46074 | W10: =V10-U10 -> 0 | X10: 46159 | Y10: 46204 | Z10: =Y10-X10 -> 45
A11: 7 | B11: PF197879 | C11: LD-00159632 | D11: MF302327 | E11: LD-00164229 | F11: ='PF MF Side by Side'!K15 -> 3300000 | G11: ='PF MF Side by Side'!L15 -> 3065000 | H11: ='PF MF Side by Side'!M15 -> -235000 | I11: ='PF MF Side by Side'!Q15 -> 340.05 | J11: ='PF MF Side by Side'!R15 -> 316.2 | K11: ='PF MF Side by Side'!S15 -> -23.85 | L11: ='PF MF Side by Side'!T15 -> 24831.71 | M11: ='PF MF Side by Side'!U15 -> 23228.14 | N11: ='PF MF Side by Side'!V15 -> -1603.57 | O11: ='PF MF Side by Side'!AI15 -> 2500 | P11: ='PF MF Side by Side'!AJ15 -> 30508 | Q11: ='PF MF Side by Side'!AK15 -> 28008 | R11: ='PF MF Side by Side'!AO15 -> 0.4939 | S11: ='PF MF Side by Side'!AP15 -> 1.0361 | T11: ='PF MF Side by Side'!AQ15 -> 54.22 | U11: 46136 | V11: 46166 | W11: =V11-U11 -> 30 | X11: 46253 | Y11: 46296 | Z11: =Y11-X11 -> 43
A12: 8 | D12: MF183562 | E12: LD-00144780 | G12: ='PF MF Side by Side'!L16 -> 935000 | J12: ='PF MF Side by Side'!R16 -> 103.9 | M12: ='PF MF Side by Side'!U16 -> 5486.43 | P12: ='PF MF Side by Side'!AJ16 -> 8519 | S12: ='PF MF Side by Side'!AP16 -> 0.8258 | X12: 46011 | Y12: 46054 | Z12: =Y12-X12 -> 43
